pyteomics-4.7.5-py3.12-nspkg.pth
pyteomics/_schema_defaults.py
pyteomics/achrom.py
pyteomics/electrochem.py
pyteomics/fasta.py
pyteomics/mgf.py
pyteomics/ms1.py
pyteomics/ms2.py
pyteomics/mzid.py
pyteomics/mzml.py
pyteomics/mzmlb.py
pyteomics/mztab.py
pyteomics/mzxml.py
pyteomics/parser.py
pyteomics/peff.py
pyteomics/pepxml.py
pyteomics/proforma.py
pyteomics/protxml.py
pyteomics/pylab_aux.py
pyteomics/tandem.py
pyteomics/traml.py
pyteomics/usi.py
pyteomics/version.py
pyteomics/xml.py
pyteomics/auxiliary/__init__.py
pyteomics/auxiliary/constants.py
pyteomics/auxiliary/file_helpers.py
pyteomics/auxiliary/math.py
pyteomics/auxiliary/patch.py
pyteomics/auxiliary/structures.py
pyteomics/auxiliary/target_decoy.py
pyteomics/auxiliary/utils.py
pyteomics/mass/__init__.py
pyteomics/mass/mass.py
pyteomics/mass/unimod.py
pyteomics/openms/__init__.py
pyteomics/openms/featurexml.py
pyteomics/openms/idxml.py
pyteomics/openms/trafoxml.py
pyteomics-4.7.5.dist-info/AUTHORS
pyteomics-4.7.5.dist-info/LICENSE
pyteomics-4.7.5.dist-info/METADATA
pyteomics-4.7.5.dist-info/NOTICE
pyteomics-4.7.5.dist-info/WHEEL
pyteomics-4.7.5.dist-info/namespace_packages.txt
pyteomics-4.7.5.dist-info/top_level.txt
pyteomics-4.7.5.dist-info/RECORD
