Metadata-Version: 2.1
Name: pyteomics
Version: 4.7.5
Summary: A framework for proteomics data analysis.
Home-page: http://pyteomics.readthedocs.io
Author: Anton Goloborodko & Lev Levitsky
Author-email: pyteomics@googlegroups.com
License: License :: OSI Approved :: Apache Software License
Project-URL: Documentation, http://pyteomics.readthedocs.io
Project-URL: Source Code, https://github.com/levitsky/pyteomics
Project-URL: Issue Tracker, https://github.com/levitsky/pyteomics/issues
Project-URL: Mailing List, https://groups.google.com/group/pyteomics
Classifier: Intended Audience :: Science/Research
Classifier: Programming Language :: Python :: 2.7
Classifier: Programming Language :: Python :: 3
Classifier: Topic :: Education
Classifier: Topic :: Scientific/Engineering :: Bio-Informatics
Classifier: Topic :: Scientific/Engineering :: Chemistry
Classifier: Topic :: Scientific/Engineering :: Physics
Classifier: Topic :: Software Development :: Libraries
License-File: LICENSE
License-File: NOTICE
License-File: AUTHORS
Provides-Extra: xml
Requires-Dist: lxml; extra == "xml"
Requires-Dist: numpy; extra == "xml"
Provides-Extra: tda
Requires-Dist: numpy; extra == "tda"
Provides-Extra: graphics
Requires-Dist: matplotlib; extra == "graphics"
Provides-Extra: df
Requires-Dist: pandas>=0.17; extra == "df"
Provides-Extra: unimod
Requires-Dist: lxml; extra == "unimod"
Requires-Dist: sqlalchemy; extra == "unimod"
Provides-Extra: numpress
Requires-Dist: pynumpress; extra == "numpress"
Provides-Extra: mzmlb
Requires-Dist: h5py; extra == "mzmlb"
Requires-Dist: hdf5plugin; extra == "mzmlb"
Provides-Extra: proforma
Requires-Dist: psims>v0.1.42; extra == "proforma"
Provides-Extra: all
Requires-Dist: scikit-learn; extra == "all"
Requires-Dist: lxml; extra == "all"
Requires-Dist: numpy; extra == "all"
Requires-Dist: numpy; extra == "all"
Requires-Dist: matplotlib; extra == "all"
Requires-Dist: pandas>=0.17; extra == "all"
Requires-Dist: lxml; extra == "all"
Requires-Dist: sqlalchemy; extra == "all"
Requires-Dist: pynumpress; extra == "all"
Requires-Dist: h5py; extra == "all"
Requires-Dist: hdf5plugin; extra == "all"
Requires-Dist: psims>v0.1.42; extra == "all"
